{
    "ColorComponent":{
        "Warm White": 0,
        "Cold White": 1,
        "Red": 2,
        "Green": 3,
        "Blue": 4,
        "Amber": 5,
        "Cyan":6,
        "Purple":7,
        "Index":8
    },
    "SetbackType":{
        "None": 0,
        "Temporary": 1,
        "Permanent": 2
    },
    "BinarySensorType": {
        "General Purpose": 1,
        "Smoke": 2,
        "CO": 3,
        "CO2": 4,
        "Heat": 5,
        "Water": 6,
        "Freeze": 7,
        "Tamper": 8,
        "Aux": 9,
        "Door/Window": 10,
        "Tilt": 11,
        "Motion": 12,
        "Glass Break": 13,
        "Any": 255
    },
    "ThermostatMode": {
        "Off": 0,
        "Heat": 1,
        "Cool": 2,
        "Auto": 3,
        "Auxiliary": 4,
        "Resume (on)": 5,
        "Fan": 6,
        "Furnace": 7,
        "Dry": 8,
        "Moist": 9,
        "Auto changeover": 10,
        "Energy heat": 11,
        "Energy cool": 12,
        "Away": 13,
        "Full power": 15,
        "Manufacturer specific": 31
    },
    "ThermostatSetpointType": {
        "N/A": 0,
        "Heating": 1,
        "Cooling": 2,
        "Furnace": 7,
        "Dry Air": 8,
        "Moist Air": 9,
        "Auto Changeover": 10,
        "Energy Save Heating": 11,
        "Energy Save Cooling": 12,
        "Away Heating": 13,
        "Away Cooling": 14,
        "Full Power": 15
    },
    "DoorLockMode": {
        "Unsecured": 0,
        "UnsecuredWithTimeout": 1,
        "InsideUnsecured": 16,
        "InsideUnsecuredWithTimeout": 17,
        "OutsideUnsecured": 32,
        "OutsideUnsecuredWithTimeout": 33,
        "Unknown": 254,
        "Secured": 255
    }
}